bashvar_sentry/__init__.py
bashvar_sentry/exceptions.py
bashvar_sentry/py.typed
bashvar_sentry/sentry.py
bashvar_sentry/resources/inspector.sh
bashvar_sentry-0.0.4.dist-info/licenses/LICENSE
bashvar_sentry-0.0.4.dist-info/METADATA
bashvar_sentry-0.0.4.dist-info/WHEEL
bashvar_sentry-0.0.4.dist-info/top_level.txt
bashvar_sentry-0.0.4.dist-info/RECORD
