Metadata-Version: 2.4
Name: bashvar_sentry
Version: 0.0.4
Summary: A robust Python module to safely source a bash script in a sandboxed environment and collect its variables.
Author-email: envolution <involution@gmail.com>
License-Expression: Apache-2.0
Project-URL: Homepage, https://github.com/envolution/bashvar-sentry
Project-URL: Issues, https://github.com/envolution/bashvar-sentry/issues
Classifier: Programming Language :: Python :: 3
Classifier: Operating System :: OS Independent
Classifier: Topic :: Software Development :: Libraries :: Python Modules
Classifier: Topic :: System :: Shells
Classifier: Development Status :: 4 - Beta
Classifier: Topic :: Utilities
Requires-Python: >=3.7
License-File: LICENSE
Requires-Dist: importlib-resources; python_version < "3.9"
Provides-Extra: test
Requires-Dist: pytest; extra == "test"
Dynamic: license-file
